ola_mundo/__init__.py
ola_mundo/funcoes.py
ola_mundo-0.0.1.dist-info/METADATA
ola_mundo-0.0.1.dist-info/WHEEL
ola_mundo-0.0.1.dist-info/top_level.txt
ola_mundo-0.0.1.dist-info/RECORD
