Metadata-Version: 2.4
Name: ola_mundo
Version: 0.0.1
Summary: Uma saudação para te livrar da maldição!
Home-page: https://github.com/josecarloslima/DIO-Suzano-Python/tree/main/ola_mundo_pkg
Author: jose_carlos_lima
Requires-Python: >=3.8
Dynamic: author
Dynamic: description
Dynamic: description-content-type
Dynamic: home-page
Dynamic: requires-python
Dynamic: summary
